aq/__init__.py
aq/__main__.py
aq/activities/__init__.py
aq/activities/activity.py
aq/activities/extract.py
aq/activities/function.py
aq/activities/generate.py
aq/activities/read.py
aq/activities/readers/__init__.py
aq/activities/readers/file.py
aq/activities/readers/pdf.py
aq/activities/readers/reader.py
aq/activities/retrieve.py
aq/activities/store.py
aq/activities/summarize.py
aq/activities/write.py
aq/broker.py
aq/containers.py
aq/http_client/__init__.py
aq/http_client/async_http_client.py
aq/jobs/__init__.py
aq/jobs/manager.py
aq/jobs/scheduler.py
aq/memory/__init__.py
aq/memory/chromadb/__init__.py
aq/memory/chromadb/repository.py
aq/memory/manager.py
aq/memory/repository.py
aq/memory/splitter.py
aq/providers/__init__.py
aq/providers/anthropic/__init__.py
aq/providers/anthropic/provider.py
aq/providers/azure/__init__.py
aq/providers/azure/provider.py
aq/providers/llava/__init__.py
aq/providers/llava/provider.py
aq/providers/manager.py
aq/providers/openai/__init__.py
aq/providers/openai/provider.py
aq/providers/provider.py
aq/providers/types/__init__.py
aq/providers/types/chat.py
aq/tools/__init__.py
aq/tools/manager.py
aq/tools/rest/__init__.py
aq/tools/rest/rest_tool.py
aq/tools/tool.py
aq/tools/web/__init__.py
aq/tools/web/web_tool.py
aq/types/__init__.py
aq/types/app.py
aq/types/job.py
pyaq-0.1.0.dist-info/LICENSE
pyaq-0.1.0.dist-info/METADATA
pyaq-0.1.0.dist-info/WHEEL
pyaq-0.1.0.dist-info/RECORD
