Metadata-Version: 2.1
Name: pyaq
Version: 0.1.0
Summary: AnyQuest Semantic Broker
Home-page: https://www.github.com/anyquest/pyaq
License: MIT
Author: Dmitri Tcherevik
Author-email: dmitri@anyquest.ai
Requires-Python: >=3.10,<3.12
Classifier: License :: OSI Approved :: MIT License
Classifier: Programming Language :: Python :: 3
Classifier: Programming Language :: Python :: 3.10
Classifier: Programming Language :: Python :: 3.11
Requires-Dist: aiofiles (>=23.2.1,<24.0.0)
Requires-Dist: bs4 (>=0.0.1,<0.0.2)
Requires-Dist: chromadb (>=0.4.18,<0.5.0)
Requires-Dist: cryptography (>=41.0.5,<42.0.0)
Requires-Dist: dependency-injector (>=4.41.0,<5.0.0)
Requires-Dist: httpx (>=0.25.2,<0.26.0)
Requires-Dist: jinja2 (>=3.1.2,<4.0.0)
Requires-Dist: jsonpath-ng (>=1.6.0,<2.0.0)
Requires-Dist: markdown (>=3.5.1,<4.0.0)
Requires-Dist: openapi3-parser (>=1.1.14,<2.0.0)
Requires-Dist: pypdf (>=3.17.1,<4.0.0)
Requires-Dist: python-dotenv (>=1.0.0,<2.0.0)
Project-URL: Repository, https://www.github.com/anyquest/pyaq
